{
    "home/anzuruna": "걱정하지 마, 바로 내가 지켜주지!\n……아니, 좀 더 물러나!\n너무 안일하다고! 위험하잖아!?",
    "home/nani_komattakotoga": "뭐야, 곤란한 일이 있나?\n왕자에게 부탁하다니 무례한 녀석!\n……에잇, 말해라! 들어보지 않으면 모른다고!",
    "home/oreno": "내 앞에서 기운 없는 얼굴 하지 마!\n우울하면 이거라도 먹어!\n먹으면 푹 자라! 알겠지!",
    "home/bi_bibittenai": "쪼, 쫀 거 아니다, 쫀 거 아니라고!\n이건, 그래! 무릎이 잠시 떨린 것뿐이다!",
    "home/doshita": "왜 그래, 풀 죽은 얼굴로.\n……그래, 전부 말 안 해도 돼.\n바로 내가 돌봐줄 테니까.",
    "ally/join": "이곳을 이세계 여행의 거점으로 삼겠다!\n자, 어떤 곳이든 데려가라!\n바로 이 몸이 지켜주지 않느냐!",
    "ally/evolution": "이제 다리 안 풀리냐고……?\n당연히 풀리지 않겠냐, 바보 녀석!\n하지만 너희만큼은 반드시 지킬 거다!"
}